scripts/__init__.py
scripts/example_parallel_jobs.py
scripts/example_single_job.py
scripts/example_sklearn_gridsearch.py
tests/__init__.py
tests/integration/__init__.py
tests/integration/test_virtual_gpu.py
tests/unit/__init__.py
tests/unit/test_virtual_gpu.py
tf2_vgpu/__init__.py
tf2_vgpu/virtual_gpu.py
tf2_vgpu-0.1.0.dist-info/METADATA
tf2_vgpu-0.1.0.dist-info/WHEEL
tf2_vgpu-0.1.0.dist-info/top_level.txt
tf2_vgpu-0.1.0.dist-info/RECORD
