Metadata-Version: 2.1
Name: tf2-vgpu
Version: 0.1.0
Summary: UNKNOWN
Home-page: https://github.com/garethjns/tf2-vgpu
Author: Gareth Jones
Author-email: garethgithub@gmail.com
License: UNKNOWN
Platform: UNKNOWN
Classifier: Programming Language :: Python :: 3
Classifier: Operating System :: OS Independent
Requires-Python: >=3.6
Requires-Dist: tensorflow (>=2.2)
Requires-Dist: joblib
Requires-Dist: numpy
Requires-Dist: dataclasses
